utils_web_scraping/__init__.py
utils_web_scraping/schemas.py
utils_web_scraping/utils_file.py
utils_web_scraping-0.1.4.dist-info/METADATA
utils_web_scraping-0.1.4.dist-info/WHEEL
utils_web_scraping-0.1.4.dist-info/top_level.txt
utils_web_scraping-0.1.4.dist-info/RECORD
